flask_wechatpy/__init__.py
Flask_wechatpy-0.1.3.dist-info/DESCRIPTION.rst
Flask_wechatpy-0.1.3.dist-info/METADATA
Flask_wechatpy-0.1.3.dist-info/metadata.json
Flask_wechatpy-0.1.3.dist-info/RECORD
Flask_wechatpy-0.1.3.dist-info/top_level.txt
Flask_wechatpy-0.1.3.dist-info/WHEEL
