Metadata-Version: 2.0
Name: Flask-wechatpy
Version: 0.1.3
Summary: wechatpy for flask extension
Home-page: https://github.com/cloverstd/flask-wechatpy
Author: cloverstd
Author-email: cloverstd@gmail.com
License: MIT
Platform: any
Classifier: Environment :: Web Environment
Classifier: Intended Audience :: Developers
Classifier: License :: OSI Approved :: MIT License
Classifier: Operating System :: OS Independent
Classifier: Programming Language :: Python
Classifier: Topic :: Internet :: WWW/HTTP :: Dynamic Content
Classifier: Topic :: Software Development :: Libraries :: Python Modules
Requires-Dist: Flask
Requires-Dist: wechatpy (>=1.2.12)
